LICENSE
LICENSE.txt
MANIFEST.in
README.md
requirements-dev.txt
requirements.txt
setup.py
alibabacloud_ros_iact3.egg-info/PKG-INFO
alibabacloud_ros_iact3.egg-info/SOURCES.txt
alibabacloud_ros_iact3.egg-info/dependency_links.txt
alibabacloud_ros_iact3.egg-info/entry_points.txt
alibabacloud_ros_iact3.egg-info/requires.txt
alibabacloud_ros_iact3.egg-info/top_level.txt
iact3/__init__.py
iact3/__main__.py
iact3/cli.py
iact3/config.py
iact3/exceptions.py
iact3/generate_params.py
iact3/logger.py
iact3/main.py
iact3/stack.py
iact3/termial_print.py
iact3/util.py
iact3/cli_modules/__init__.py
iact3/cli_modules/base.py
iact3/cli_modules/cost.py
iact3/cli_modules/delete.py
iact3/cli_modules/list.py
iact3/cli_modules/policy.py
iact3/cli_modules/preview.py
iact3/cli_modules/test.py
iact3/cli_modules/validate.py
iact3/plugin/__init__.py
iact3/plugin/base_plugin.py
iact3/plugin/ecs.py
iact3/plugin/error_code.py
iact3/plugin/oss.py
iact3/plugin/ros.py
iact3/plugin/vpc.py
iact3/report/__init__.py
iact3/report/generate_reports.py
iact3/report/html.css
iact3/testing/__init__.py
iact3/testing/base.py
iact3/testing/ros_stack.py