Metadata-Version: 2.1
Name: alibabacloud-ros-iact3
Version: 0.1.12
Summary: Iact3 is a tool that tests Terraform and ROS(Resource Orchestration Service) templates.
Author: AlibabaCloud
Classifier: Development Status :: 2 - Pre-Alpha
Classifier: Intended Audience :: Developers
Classifier: License :: OSI Approved :: Apache Software License
Classifier: Programming Language :: Python :: 3.7
Classifier: Programming Language :: Python :: 3.8
Classifier: Topic :: Software Development :: Libraries
Classifier: Topic :: Software Development :: Testing
Classifier: Operating System :: POSIX :: Linux
Classifier: Operating System :: MacOS :: MacOS X 
Requires-Python: >=3.7
License-File: LICENSE
License-File: LICENSE.txt
